{
    "Booths": {
        "Extra": {
            "BoothServerHop": true,
            "BoothServerHopTime": "30",
            "BoothServerHopTimeMax": "60",
            "HopToMaxPing": "100",
            "HopToMinFps": "10",
            "MinimumPlayers": "30",
            "TeleportToBooth": true
        },
        "Selling": {
            "autoMultipliers": {
                "DMmulti": "15",
                "enableDM": false,
                "enableG": false,
                "enableHC": false,
                "enableRB": false,
                "enableSH": false,
                "Gmulti": "2.5",
                "HCmulti": "3",
                "RBmulti": "6.5",
                "SHmulti": "2"
            },
            "SellingList": [
                {
                    "Class": "Pet",
                    "IsHuge": true,
                    "UnitPrice": 0
                },
                {
                    "Class": "Pet",
                    "Rarity": [
                        "Exclusive"
                    ],
                    "UnitPrice": 0
                },
                {
                    "Class": "Pet",
                    "Rarity": [
                        "Celestial",
                        "Superior",
                        "Divine",
                        "Exotic",
                        "Mythical",
                        "Legendary",
                        "Epic",
                        "Rare",
                        "Basic"
                    ],
                    "UnitPrice": 0,
                    "MaxStackSize": 5000
                },
                {
                    "Class": "XPPotion",
                    "UnitPrice": 0,
                    "MaxStackSize": 5000
                },
                {
                    "Class": "Fruit",
                    "UnitPrice": 0,
                    "MaxStackSize": 5000
                },
                {
                    "Class": "Enchant",
                    "UnitPrice": 0,
                    "MaxStackSize": 5000
                },
                {
                    "Class": "Potion",
                    "UnitPrice": 0,
                    "MaxStackSize": 5000
                },
                {
                    "Class": "Misc",
                    "UnitPrice": 0,
                    "MaxStackSize": 5000
                },
                {
                    "Class": "Booth",
                    "UnitPrice": 0,
                    "MaxStackSize": 5000
                },
                {
                    "Class": "Lootbox",
                    "UnitPrice": 0,
                    "MaxStackSize": 5000
                },
                {
                    "Class": "Charm",
                    "UnitPrice": 0,
                    "MaxStackSize": 5000
                },
                {
                    "Class": "Ultimate",
                    "UnitPrice": 0,
                    "MaxStackSize": 5000
                },
                {
                    "Class": "Hoverboard",
                    "UnitPrice": 0,
                    "MaxStackSize": 5000
                },
                {
                    "Class": "Egg",
                    "UnitPrice": 0,
                    "MaxStackSize": 5000
                }
            ],
            "StartSellingPet": true,
            "MinPower": 3000000000,
            "RAPDiscountPercentage": 1
        },
        "Sniping": {
            "StartSnipingPet": true,
            "AutoRapBuy": true,
            "HopAfterHuge": true,
            "MinimumGemsWarning": 25000000,
            "MinPower": 72000000000000,
            "BlackList": [
                "Old Boot",
                "Snowball",
                "Enchant Essence",
                "Magnet",
                "Comet",
                "Graffiti Can",
                "Rainbow Swirl"
            ],
            "SnipingList": [
                {
                    "Class": "Pet",
                    "IsTitanic": true,
                    "MaxUnitPrice": 1500000001
                },
                {
                    "Class": "Pet",
                    "Type": "Exclusive",
                    "IsHuge": true,
                    "IsRainbow": true,
                    "MaxUnitPrice": 90000000,
                    "RapBuy": true
                },
                {
                    "Class": "Pet",
                    "Type": "Exclusive",
                    "IsHuge": true,
                    "IsShiny": true,
                    "IsRainbow": true,
                    "MaxUnitPrice": 90000000,
                    "RapBuy": true
                },
                {
                    "Class": "Pet",
                    "Type": "Exclusive",
                    "IsHuge": true,
                    "IsShiny": true,
                    "MaxUnitPrice": 75000000,
                    "RapBuy": true
                },
                {
                    "Class": "Pet",
                    "Type": "Exclusive",
                    "IsHuge": true,
                    "IsGolden": true,
                    "MaxUnitPrice": 35000000,
                    "RapBuy": true
                },
                {
                    "Class": "Pet",
                    "Type": "Exclusive",
                    "IsHuge": true,
                    "MaxUnitPrice": 30000000,
                    "RapBuy": true
                },
                {
                    "Class": "Pet",
                    "Type": "Exclusive",
                    "IsGolden": true,
                    "MaxUnitPrice": 750000,
                    "RapBuy": true
                },
                {
                    "Class": "Pet",
                    "Type": "Exclusive",
                    "IsRainbow": true,
                    "MaxUnitPrice": 1000000,
                    "RapBuy": true
                },
                {
                    "Class": "Pet",
                    "Type": "Exclusive",
                    "MaxUnitPrice": 500000,
                    "RapBuy": true
                },
                {
                    "Class": "Pet",
                    "Rarity": [
                        "Celestial",
                        "Superior",
                        "Divine",
                        "Exotic",
                        "Mythical",
                        "Legendary",
                        "Epic",
                        "Rare",
                        "Basic"
                    ],
                    "MaxUnitPrice": 250,
                    "RapBuy": true
                },
                            {
        "Class": "Potion",
        "Id": "Damage",
        "MinTier": 11,
        "MaxUnitPrice": 81276
    },
    {
        "Class": "Potion",
        "Id": "Treasure Hunter",
        "MinTier": 11,
        "MaxUnitPrice": 772608
    },
    {
        "Class": "Potion",
        "Id": "Coins",
        "MinTier": 11,
        "MaxUnitPrice": 23462
    },
    {
        "Class": "Potion",
        "Id": "Lucky",
        "MinTier": 11,
        "MaxUnitPrice": 397578
    },
    {
        "Class": "Potion",
        "Id": "Lucky",
        "MinTier": 10,
        "MaxUnitPrice": 18905
    },
    {
        "Class": "Potion",
        "Id": "Damage",
        "MinTier": 10,
        "MaxUnitPrice": 1123
    },
    {
        "Class": "Potion",
        "Id": "Coins",
        "MinTier": 10,
        "MaxUnitPrice": 410
    },
    {
        "Class": "Potion",
        "Id": "Treasure Hunter",
        "MinTier": 10,
        "MaxUnitPrice": 117041
    },
    {
        "Class": "Enchant",
        "Id": "Criticals",
        "MinTier": 10,
        "MaxUnitPrice": 701787
    },
    {
        "Class": "Enchant",
        "Id": "Diamonds",
        "MinTier": 10,
        "MaxUnitPrice": 813550
    },
    {
        "Class": "Enchant",
        "Id": "Tap Power",
        "MinTier": 10,
        "MaxUnitPrice": 317151
    },
    {
        "Class": "Enchant",
        "Id": "Lucky Eggs",
        "MinTier": 10,
        "MaxUnitPrice": 1948691
    },
    {
        "Class": "Enchant",
        "Id": "Coins",
        "MinTier": 10,
        "MaxUnitPrice": 585203
    },
    {
        "Class": "Enchant",
        "Id": "Strong Pets",
        "MinTier": 10,
        "MaxUnitPrice": 504878
    },
    {
        "Class": "Enchant",
        "Id": "Treasure Hunter",
        "MinTier": 10,
        "MaxUnitPrice": 558061
    },
    {
        "Class": "Potion",
        "Id": "Diamonds",
        "MinTier": 9,
        "MaxUnitPrice": 44056
    },
    {
        "Class": "Potion",
        "Id": "Treasure Hunter",
        "MinTier": 9,
        "MaxUnitPrice": 1182
    },
    {
        "Class": "Potion",
        "Id": "Coins",
        "MinTier": 9,
        "MaxUnitPrice": 1190
    },
    {
        "Class": "Potion",
        "Id": "Damage",
        "MinTier": 9,
        "MaxUnitPrice": 751
    },
    {
        "Class": "Potion",
        "Id": "Lucky",
        "MinTier": 9,
        "MaxUnitPrice": 1140
    },
    {
        "Class": "Enchant",
        "Id": "Lucky Eggs",
        "MinTier": 9,
        "MaxUnitPrice": 223422
    },
    {
        "Class": "Enchant",
        "Id": "Diamonds",
        "MinTier": 9,
        "MaxUnitPrice": 18936
    },
    {
        "Class": "Enchant",
        "Id": "Strong Pets",
        "MinTier": 9,
        "MaxUnitPrice": 11640
    },
    {
        "Class": "Enchant",
        "Id": "Coins",
        "MinTier": 9,
        "MaxUnitPrice": 10063
    },
    {
        "Class": "Enchant",
        "Id": "Tap Power",
        "MinTier": 9,
        "MaxUnitPrice": 8577
    },
    {
        "Class": "Enchant",
        "Id": "Criticals",
        "MinTier": 9,
        "MaxUnitPrice": 18965
    },
    {
        "Class": "Enchant",
        "Id": "Treasure Hunter",
        "MinTier": 9,
        "MaxUnitPrice": 17230
    },
    {
        "Class": "Potion",
        "Id": "Coins",
        "MinTier": 8,
        "MaxUnitPrice": 397
    },
    {
        "Class": "Potion",
        "Id": "Damage",
        "MinTier": 8,
        "MaxUnitPrice": 791
    },
    {
        "Class": "Potion",
        "Id": "Lucky",
        "MinTier": 8,
        "MaxUnitPrice": 2206
    },
    {
        "Class": "Potion",
        "Id": "Treasure Hunter",
        "MinTier": 8,
        "MaxUnitPrice": 391
    },
    {
        "Class": "Potion",
        "Id": "Diamonds",
        "MinTier": 8,
        "MaxUnitPrice": 1210
    },
    {
        "Class": "Enchant",
        "Id": "Lucky Eggs",
        "MinTier": 8,
        "MaxUnitPrice": 37370
    },
    {
        "Class": "Enchant",
        "Id": "Tap Power",
        "MinTier": 8,
        "MaxUnitPrice": 488
    },
    {
        "Class": "Enchant",
        "Id": "Diamonds",
        "MinTier": 8,
        "MaxUnitPrice": 780
    },
    {
        "Class": "Enchant",
        "Id": "Coins",
        "MinTier": 8,
        "MaxUnitPrice": 1995
    },
    {
        "Class": "Enchant",
        "Id": "Treasure Hunter",
        "MinTier": 8,
        "MaxUnitPrice": 1084
    },
    {
        "Class": "Enchant",
        "Id": "Strong Pets",
        "MinTier": 8,
        "MaxUnitPrice": 937
    },
    {
        "Class": "Enchant",
        "Id": "Criticals",
        "MinTier": 8,
        "MaxUnitPrice": 1135
    },
    {
        "Class": "Potion",
        "Id": "Treasure Hunter",
        "MinTier": 7,
        "MaxUnitPrice": 78
    },
    {
        "Class": "Potion",
        "Id": "Coins",
        "MinTier": 7,
        "MaxUnitPrice": 119
    },
    {
        "Class": "Potion",
        "Id": "Damage",
        "MinTier": 7,
        "MaxUnitPrice": 119
    },
    {
        "Class": "Potion",
        "Id": "Diamonds",
        "MinTier": 7,
        "MaxUnitPrice": 167
    },
    {
        "Class": "Potion",
        "Id": "Lucky",
        "MinTier": 7,
        "MaxUnitPrice": 160
    },
    {
        "Class": "Enchant",
        "Id": "Tap Power",
        "MinTier": 7,
        "MaxUnitPrice": 208
    },
    {
        "Class": "Enchant",
        "Id": "Lucky Eggs",
        "MinTier": 7,
        "MaxUnitPrice": 9726
    },
    {
        "Class": "Enchant",
        "Id": "Coins",
        "MinTier": 7,
        "MaxUnitPrice": 4213
    },
    {
        "Class": "Enchant",
        "Id": "Diamonds",
        "MinTier": 7,
        "MaxUnitPrice": 615
    },
    {
        "Class": "Enchant",
        "Id": "Treasure Hunter",
        "MinTier": 7,
        "MaxUnitPrice": 298
    },
    {
        "Class": "Enchant",
        "Id": "Criticals",
        "MinTier": 7,
        "MaxUnitPrice": 178
    },
    {
        "Class": "Enchant",
        "Id": "Strong Pets",
        "MinTier": 7,
        "MaxUnitPrice": 308
    },
    {
        "Class": "Potion",
        "Id": "Diamonds",
        "MinTier": 6,
        "MaxUnitPrice": 143
    },
    {
        "Class": "Potion",
        "Id": "Treasure Hunter",
        "MinTier": 6,
        "MaxUnitPrice": 77
    },
    {
        "Class": "Potion",
        "Id": "Lucky",
        "MinTier": 6,
        "MaxUnitPrice": 100
    },
    {
        "Class": "Potion",
        "Id": "Damage",
        "MinTier": 6,
        "MaxUnitPrice": 115
    },
    {
        "Class": "Potion",
        "Id": "Coins",
        "MinTier": 6,
        "MaxUnitPrice": 33
    },
    {
        "Class": "Enchant",
        "Id": "Diamonds",
        "MinTier": 6,
        "MaxUnitPrice": 169
    },
    {
        "Class": "Enchant",
        "Id": "Lucky Eggs",
        "MinTier": 6,
        "MaxUnitPrice": 224
    },
    {
        "Class": "Enchant",
        "Id": "Treasure Hunter",
        "MinTier": 6,
        "MaxUnitPrice": 36
    },
    {
        "Class": "Enchant",
        "Id": "Coins",
        "MinTier": 6,
        "MaxUnitPrice": 427
    },
    {
        "Class": "Enchant",
        "Id": "Tap Power",
        "MinTier": 6,
        "MaxUnitPrice": 82
    },
    {
        "Class": "Enchant",
        "Id": "Strong Pets",
        "MinTier": 6,
        "MaxUnitPrice": 72
    },
    {
        "Class": "Enchant",
        "Id": "Criticals",
        "MinTier": 6,
        "MaxUnitPrice": 36
    },
    {
        "Class": "Potion",
        "Id": "Diamonds",
        "MinTier": 5,
        "MaxUnitPrice": 29
    },
    {
        "Class": "Potion",
        "Id": "Lucky",
        "MinTier": 5,
        "MaxUnitPrice": 36
    },
    {
        "Class": "Potion",
        "Id": "Coins",
        "MinTier": 5,
        "MaxUnitPrice": 9
    },
    {
        "Class": "Potion",
        "Id": "Damage",
        "MinTier": 5,
        "MaxUnitPrice": 22
    },
    {
        "Class": "Potion",
        "Id": "Treasure Hunter",
        "MinTier": 5,
        "MaxUnitPrice": 17
    },
    {
        "Class": "Potion",
        "Id": "Huge",
        "MinTier": 1,
        "MaxUnitPrice": 269781
    },
    {
        "Class": "Potion",
        "Id": "The Cocktail",
        "MinTier": 1,
        "MaxUnitPrice": 25659
    },
    {
        "Class": "XPPotion",
        "Id": "Huge",
        "MaxUnitPrice": 256157
    },
    {
        "Class": "XPPotion",
        "Id": "Mastery",
        "MaxUnitPrice": 142378
    },
    {
        "Class": "Charm",
        "Id": "XP",
        "MaxUnitPrice": 7683
    },
    {
        "Class": "Charm",
        "Id": "Royalty",
        "MaxUnitPrice": 826830
    },
    {
        "Class": "Charm",
        "Id": "Overload",
        "MaxUnitPrice": 1401313
    },
    {
        "Class": "Charm",
        "Id": "Glittering",
        "MaxUnitPrice": 11532
    },
    {
        "Class": "Misc",
        "Id": "Ultra Pet Cube",
        "MaxUnitPrice": 459
    },
    {
        "Class": "Misc",
        "Id": "Pet Cube",
        "MaxUnitPrice": 22
    },
    {
        "Class": "Misc",
        "Id": "Graffiti Can",
        "MaxUnitPrice": 11
    },
    {
        "Class": "Misc",
        "Id": "Candy Corn",
        "MaxUnitPrice": 750
    },
    {
        "Class": "Misc",
        "Id": "Rave Upgrade Ticket",
        "MaxUnitPrice": 701
    },
    {
        "Class": "Misc",
        "Id": "Pumpkin",
        "MaxUnitPrice": 1793
    },
    {
        "Class": "Misc",
        "Id": "Diamond Gift Bag",
        "MaxUnitPrice": 7826
    },
    {
        "Class": "Misc",
        "Id": "Prison Key",
        "MaxUnitPrice": 6694
    },
    {
        "Class": "Misc",
        "Id": "Void Key Lower Half",
        "MaxUnitPrice": 169
    },
    {
        "Class": "Misc",
        "Id": "Void Spinny Wheel Ticket",
        "MaxUnitPrice": 7066
    },
    {
        "Class": "Misc",
        "Id": "Nightmare Fuel",
        "MaxUnitPrice": 42617
    },
    {
        "Class": "Misc",
        "Id": "Millionaire Ticket",
        "MaxUnitPrice": 2851
    },
    {
        "Class": "Misc",
        "Id": "Legendary Glitch Core",
        "MaxUnitPrice": 72085
    },
    {
        "Class": "Misc",
        "Id": "Rare Glitch Core",
        "MaxUnitPrice": 12236
    },
    {
        "Class": "Misc",
        "Id": "Epic Glitch Core",
        "MaxUnitPrice": 6740
    },
    {
        "Class": "Misc",
        "Id": "Treasure Hideout Key Lower Half",
        "MaxUnitPrice": 13
    },
    {
        "Class": "Misc",
        "Id": "Treasure Hideout Key",
        "MaxUnitPrice": 3741
    },
    {
        "Class": "Misc",
        "Id": "Basic Item Jar",
        "MaxUnitPrice": 3881
    },
    {
        "Class": "Misc",
        "Id": "Exclusive Daycare Slot Voucher",
        "MaxUnitPrice": 4982789
    },
    {
        "Class": "Misc",
        "Id": "Arcade Token",
        "MaxUnitPrice": 3251
    },
    {
        "Class": "Misc",
        "Id": "Large Enchant Bundle",
        "MaxUnitPrice": 60
    },
    {
        "Class": "Misc",
        "Id": "Fruit Bundle",
        "MaxUnitPrice": 39
    },
    {
        "Class": "Misc",
        "Id": "Charm Chisel",
        "MaxUnitPrice": 6943
    },
    {
        "Class": "Misc",
        "Id": "Tech Key Lower Half",
        "MaxUnitPrice": 154
    },
    {
        "Class": "Misc",
        "Id": "Hacker Key",
        "MaxUnitPrice": 3942
    },
    {
        "Class": "Misc",
        "Id": "Tech Key",
        "MaxUnitPrice": 4405
    },
    {
        "Class": "Misc",
        "Id": "Diamond Shovel",
        "MaxUnitPrice": 1162469
    },
    {
        "Class": "Misc",
        "Id": "Magic Shard",
        "MaxUnitPrice": 11498
    },
    {
        "Class": "Misc",
        "Id": "Treasure Hideout Key Upper Half",
        "MaxUnitPrice": 206
    },
    {
        "Class": "Misc",
        "Id": "Secret Key Upper Half",
        "MaxUnitPrice": 752
    },
    {
        "Class": "Misc",
        "Id": "Void Key Upper Half",
        "MaxUnitPrice": 2672
    },
    {
        "Class": "Misc",
        "Id": "Charm Stone",
        "MaxUnitPrice": 3314
    },
    {
        "Class": "Misc",
        "Id": "Golden Fishing Rod",
        "MaxUnitPrice": 9317
    },
    {
        "Class": "Misc",
        "Id": "Firework Cannon",
        "MaxUnitPrice": 5614
    },
    {
        "Class": "Misc",
        "Id": "Squeaky Toy",
        "MaxUnitPrice": 7
    },
    {
        "Class": "Misc",
        "Id": "Hot Cocoa",
        "MaxUnitPrice": 954
    },
    {
        "Class": "Misc",
        "Id": "Green Christmas Ornament",
        "MaxUnitPrice": 89901
    },
    {
        "Class": "Misc",
        "Id": "Coins Flag",
        "MaxUnitPrice": 2
    },
    {
        "Class": "Misc",
        "Id": "Basic Glitch Core",
        "MaxUnitPrice": 35002
    },
    {
        "Class": "Misc",
        "Id": "Diamond Fishing Rod",
        "MaxUnitPrice": 2222723
    },
    {
        "Class": "Misc",
        "Id": "Gold Christmas Ornament",
        "MaxUnitPrice": 11567
    },
    {
        "Class": "Misc",
        "Id": "Old Boot",
        "MaxUnitPrice": 204
    },
    {
        "Class": "Misc",
        "Id": "Void Key",
        "MaxUnitPrice": 12506
    },
    {
        "Class": "Misc",
        "Id": "Crystal Key Lower Half",
        "MaxUnitPrice": 99
    },
    {
        "Class": "Misc",
        "Id": "TNT Crate",
        "MaxUnitPrice": 151
    },
    {
        "Class": "Misc",
        "Id": "Water Gun",
        "MaxUnitPrice": 306805
    },
    {
        "Class": "Misc",
        "Id": "Daycare Slot Voucher",
        "MaxUnitPrice": 251
    },
    {
        "Class": "Misc",
        "Id": "Basic Coin Jar",
        "MaxUnitPrice": 2
    },
    {
        "Class": "Misc",
        "Id": "Blue Christmas Ornament",
        "MaxUnitPrice": 47821
    },
    {
        "Class": "Misc",
        "Id": "Glitched Drive",
        "MaxUnitPrice": 283470
    },
    {
        "Class": "Misc",
        "Id": "Crystal Key",
        "MaxUnitPrice": 2866
    },
    {
        "Class": "Misc",
        "Id": "Fireworks",
        "MaxUnitPrice": 332
    },
    {
        "Class": "Misc",
        "Id": "Golden Prison Key",
        "MaxUnitPrice": 47723
    },
    {
        "Class": "Misc",
        "Id": "Rainbow Mini Chest",
        "MaxUnitPrice": 138221
    },
    {
        "Class": "Misc",
        "Id": "Strength Flag",
        "MaxUnitPrice": 8
    },
    {
        "Class": "Misc",
        "Id": "Enchant Bundle",
        "MaxUnitPrice": 22
    },
    {
        "Class": "Misc",
        "Id": "Breakable Sprinkler",
        "MaxUnitPrice": 157
    },
    {
        "Class": "Misc",
        "Id": "Insta Plant Capsule",
        "MaxUnitPrice": 2944
    },
    {
        "Class": "Misc",
        "Id": "Mini Pinata",
        "MaxUnitPrice": 4119
    },
    {
        "Class": "Misc",
        "Id": "Booth Slot Voucher",
        "MaxUnitPrice": 2473
    },
    {
        "Class": "Misc",
        "Id": "Toy Bone",
        "MaxUnitPrice": 2
    },
    {
        "Class": "Misc",
        "Id": "Fortune Flag",
        "MaxUnitPrice": 11
    },
    {
        "Class": "Misc",
        "Id": "Enchant Essence",
        "MaxUnitPrice": 49
    },
    {
        "Class": "Misc",
        "Id": "Golden Shovel",
        "MaxUnitPrice": 4679
    },
    {
        "Class": "Misc",
        "Id": "Nametag",
        "MaxUnitPrice": 3
    },
    {
        "Class": "Misc",
        "Id": "Large Gift Bag",
        "MaxUnitPrice": 2056
    },
    {
        "Class": "Misc",
        "Id": "Toy Ball",
        "MaxUnitPrice": 2
    },
    {
        "Class": "Misc",
        "Id": "Clan Voucher",
        "MaxUnitPrice": 7294448
    },
    {
        "Class": "Misc",
        "Id": "Gift Bag",
        "MaxUnitPrice": 589
    },
    {
        "Class": "Misc",
        "Id": "Hasty Flag",
        "MaxUnitPrice": 5
    },
    {
        "Class": "Misc",
        "Id": "Red Christmas Ornament",
        "MaxUnitPrice": 4633
    },
    {
        "Class": "Misc",
        "Id": "Giant Coin Jar",
        "MaxUnitPrice": 2
    },
    {
        "Class": "Misc",
        "Id": "Spinny Wheel Ticket",
        "MaxUnitPrice": 696
    },
    {
        "Class": "Misc",
        "Id": "Tech Key Upper Half",
        "MaxUnitPrice": 1126
    },
    {
        "Class": "Misc",
        "Id": "Diamonds Flag",
        "MaxUnitPrice": 5
    },
    {
        "Class": "Misc",
        "Id": "Comet",
        "MaxUnitPrice": 108
    },
    {
        "Class": "Misc",
        "Id": "Rainbow Swirl",
        "MaxUnitPrice": 567
    },
    {
        "Class": "Misc",
        "Id": "Crystal Key Upper Half",
        "MaxUnitPrice": 637
    },
    {
        "Class": "Misc",
        "Id": "Tech Spinny Wheel Ticket",
        "MaxUnitPrice": 1146
    },
    {
        "Class": "Misc",
        "Id": "Magic Coin Jar",
        "MaxUnitPrice": 2
    },
    {
        "Class": "Misc",
        "Id": "Potion Bundle",
        "MaxUnitPrice": 14
    },
    {
        "Class": "Misc",
        "Id": "Toy Bundle",
        "MaxUnitPrice": 14
    },
    {
        "Class": "Misc",
        "Id": "Shiny Flag",
        "MaxUnitPrice": 60
    },
    {
        "Class": "Misc",
        "Id": "Charm Hammer",
        "MaxUnitPrice": 905
    },
    {
        "Class": "Misc",
        "Id": "Seed Bag",
        "MaxUnitPrice": 1337
    },
    {
        "Class": "Misc",
        "Id": "Rainbow Flag",
        "MaxUnitPrice": 99
    },
    {
        "Class": "Misc",
        "Id": "Magnet Flag",
        "MaxUnitPrice": 10
    },
    {
        "Class": "Misc",
        "Id": "Snowball Launcher",
        "MaxUnitPrice": 368
    },
    {
        "Class": "Misc",
        "Id": "Snowball",
        "MaxUnitPrice": 11
    },
    {
        "Class": "Misc",
        "Id": "Secret Key Lower Half",
        "MaxUnitPrice": 178
    },
    {
        "Class": "Misc",
        "Id": "TNT",
        "MaxUnitPrice": 2
    },
    {
        "Class": "Misc",
        "Id": "Christmas Cookie",
        "MaxUnitPrice": 2069
    },
    {
        "Class": "Misc",
        "Id": "Silver Christmas Ornament",
        "MaxUnitPrice": 31308
    },
    {
        "Class": "Misc",
        "Id": "Bucket",
        "MaxUnitPrice": 1034
    },
    {
        "Class": "Misc",
        "Id": "Pink Christmas Ornament",
        "MaxUnitPrice": 18787
    },
    {
        "Class": "Misc",
        "Id": "Golden Watering Can",
        "MaxUnitPrice": 9923
    },
    {
        "Class": "Misc",
        "Id": "Exotic Treasure Flag",
        "MaxUnitPrice": 62642
    },
    {
        "Class": "Misc",
        "Id": "Large Potion Bundle",
        "MaxUnitPrice": 264
    },
    {
        "Class": "Misc",
        "Id": "Bucket O' Magic",
        "MaxUnitPrice": 12958
    },
    {
        "Class": "Misc",
        "Id": "Mini Lucky Block",
        "MaxUnitPrice": 151
    },
    {
        "Class": "Misc",
        "Id": "Mystery Ticket",
        "MaxUnitPrice": 15227572
    },
    {
        "Class": "Misc",
        "Id": "Secret Key",
        "MaxUnitPrice": 5073
    },
    {
        "Class": "Misc",
        "Id": "Party Box",
        "MaxUnitPrice": 201
    },
    {
        "Class": "Misc",
        "Id": "Mini Chest",
        "MaxUnitPrice": 1851
    },
    {
        "Class": "Misc",
        "Id": "Flag Bundle",
        "MaxUnitPrice": 20
    },
    {
        "Class": "Misc",
        "Id": "Mythical Glitch Core",
        "MaxUnitPrice": 332105
    },
    {
        "Class": "Misc",
        "Id": "Slingshot",
        "MaxUnitPrice": 5608
    },
    {
        "Class": "Egg",
        "Id": "Series 3 Mythical Gift",
        "MaxUnitPrice": 199747040
    },
    {
        "Class": "Egg",
        "Id": "Series 3 Epic Gift",
        "MaxUnitPrice": 61763251
    },
    {
        "Class": "Egg",
        "Id": "Exclusive Egg 30",
        "MaxUnitPrice": 14645046
    },
    {
        "Class": "Egg",
        "Id": "Huge Machine Egg 4",
        "MaxUnitPrice": 76091624
    },
    {
        "Class": "Egg",
        "Id": "Exclusive Egg 28",
        "MaxUnitPrice": 15863283
    },
    {
        "Class": "Egg",
        "Id": "Exclusive Egg 27",
        "MaxUnitPrice": 14643635
    },
    {
        "Class": "Egg",
        "Id": "Exclusive Egg 24",
        "MaxUnitPrice": 15167522
    },
    {
        "Class": "Egg",
        "Id": "Exclusive Egg 23",
        "MaxUnitPrice": 15044906
    },
    {
        "Class": "Egg",
        "Id": "Huge Machine Egg 3",
        "MaxUnitPrice": 76327668
    },
    {
        "Class": "Egg",
        "Id": "Active Huge Egg",
        "MaxUnitPrice": 48782602
    },
    {
        "Class": "Egg",
        "Id": "Exclusive Egg 22",
        "MaxUnitPrice": 20960008
    },
    {
        "Class": "Egg",
        "Id": "Exclusive Egg 21",
        "MaxUnitPrice": 18888751
    },
    {
        "Class": "Egg",
        "Id": "Exclusive Egg 26",
        "MaxUnitPrice": 16659722
    },
    {
        "Class": "Egg",
        "Id": "Exclusive Egg 20",
        "MaxUnitPrice": 15337667
    },
    {
        "Class": "Egg",
        "Id": "Exclusive Egg 32",
        "MaxUnitPrice": 15219107
    },
    {
        "Class": "Egg",
        "Id": "Series 1 Epic Gift",
        "MaxUnitPrice": 15161744
    },
    {
        "Class": "Egg",
        "Id": "Exclusive Egg 9",
        "MaxUnitPrice": 52852726
    },
    {
        "Class": "Egg",
        "Id": "Series 1 Rare Gift",
        "MaxUnitPrice": 12824167
    },
    {
        "Class": "Egg",
        "Id": "Series 2 Mythical Gift",
        "MaxUnitPrice": 69763417
    },
    {
        "Class": "Egg",
        "Id": "Exclusive Egg 19",
        "MaxUnitPrice": 18022180
    },
    {
        "Class": "Egg",
        "Id": "Series 1 Legendary Gift",
        "MaxUnitPrice": 30154380
    },
    {
        "Class": "Egg",
        "Id": "Event Egg 1",
        "MaxUnitPrice": 9000031
    },
    {
        "Class": "Egg",
        "Id": "Exclusive Egg 14",
        "MaxUnitPrice": 57109928
    },
    {
        "Class": "Egg",
        "Id": "Series 2 Epic Gift",
        "MaxUnitPrice": 13940007
    },
    {
        "Class": "Egg",
        "Id": "Exclusive Egg 13",
        "MaxUnitPrice": 20272476
    },
    {
        "Class": "Egg",
        "Id": "Huge Machine Egg 2",
        "MaxUnitPrice": 63045547
    },
    {
        "Class": "Egg",
        "Id": "Exclusive Egg 5",
        "MaxUnitPrice": 96554661
    },
    {
        "Class": "Egg",
        "Id": "Exclusive Egg 15",
        "MaxUnitPrice": 36440056
    },
    {
        "Class": "Egg",
        "Id": "Exclusive Egg 3",
        "MaxUnitPrice": 1102176329
    },
    {
        "Class": "Egg",
        "Id": "Exclusive Egg 12",
        "MaxUnitPrice": 20348351
    },
    {
        "Class": "Egg",
        "Id": "Series 2 Basic Gift",
        "MaxUnitPrice": 8751218
    },
    {
        "Class": "Egg",
        "Id": "Series 1 Mythical Gift",
        "MaxUnitPrice": 83469292
    },
    {
        "Class": "Egg",
        "Id": "Exclusive Egg 33",
        "MaxUnitPrice": 14346014
    },
    {
        "Class": "Egg",
        "Id": "Series 1 Basic Gift",
        "MaxUnitPrice": 15486570
    },
    {
        "Class": "Egg",
        "Id": "Exclusive Egg 36",
        "MaxUnitPrice": 14052139
    },
    {
        "Class": "Egg",
        "Id": "Exclusive Egg 11",
        "MaxUnitPrice": 22862569
    },
    {
        "Class": "Egg",
        "Id": "Exclusive Egg 31",
        "MaxUnitPrice": 26346532
    },
    {
        "Class": "Egg",
        "Id": "Exclusive Egg 10",
        "MaxUnitPrice": 29352814
    },
    {
        "Class": "Egg",
        "Id": "Exclusive Egg 8",
        "MaxUnitPrice": 56524742
    },
    {
        "Class": "Egg",
        "Id": "Series 3 Legendary Gift",
        "MaxUnitPrice": 68536776
    },
    {
        "Class": "Egg",
        "Id": "Series 2 Rare Gift",
        "MaxUnitPrice": 10786388
    },
    {
        "Class": "Egg",
        "Id": "Exclusive Egg 2",
        "MaxUnitPrice": 452499204
    },
    {
        "Class": "Egg",
        "Id": "Exclusive Egg 7",
        "MaxUnitPrice": 46525250
    },
    {
        "Class": "Egg",
        "Id": "Exclusive Egg 29",
        "MaxUnitPrice": 15022616
    },
    {
        "Class": "Egg",
        "Id": "Exclusive Egg 17",
        "MaxUnitPrice": 37728416
    },
    {
        "Class": "Egg",
        "Id": "Exclusive Egg 6",
        "MaxUnitPrice": 76904823
    },
    {
        "Class": "Egg",
        "Id": "Exclusive Egg 16",
        "MaxUnitPrice": 22021160
    },
    {
        "Class": "Egg",
        "Id": "Series 2 Legendary Gift",
        "MaxUnitPrice": 27884437
    },
    {
        "Class": "Egg",
        "Id": "Exclusive Egg 35",
        "MaxUnitPrice": 15158677
    },
    {
        "Class": "Egg",
        "Id": "Exclusive Egg 34",
        "MaxUnitPrice": 18411054
    },
    {
        "Class": "Egg",
        "Id": "Exclusive Egg 4",
        "MaxUnitPrice": 126066619
    },
    {
        "Class": "Egg",
        "Id": "Exclusive Egg 25",
        "MaxUnitPrice": 32476367
    },
    {
        "Class": "Egg",
        "Id": "Exclusive Egg 18",
        "MaxUnitPrice": 17263119
    },
    {
        "Class": "Egg",
        "Id": "Huge Machine Egg 1",
        "MaxUnitPrice": 236887761
    },
    {
        "Class": "Egg",
        "Id": "Exclusive Egg 1",
        "MaxUnitPrice": 337963104
    },
    {
        "Class": "Booth",
        "Id": "Cauldron",
        "MaxUnitPrice": 106610
    },
    {
        "Class": "Booth",
        "Id": "Pumpkin Cat",
        "MaxUnitPrice": 209059
    },
    {
        "Class": "Booth",
        "Id": "Vampire",
        "MaxUnitPrice": 1951294
    },
    {
        "Class": "Booth",
        "Id": "Reversed",
        "MaxUnitPrice": 28224968
    },
    {
        "Class": "Booth",
        "Id": "Elemental",
        "MaxUnitPrice": 37712
    },
    {
        "Class": "Booth",
        "Id": "Galaxy",
        "MaxUnitPrice": 17933322
    },
    {
        "Class": "Booth",
        "Id": "Money",
        "MaxUnitPrice": 5390360
    },
    {
        "Class": "Booth",
        "Id": "Strawberry",
        "MaxUnitPrice": 201740
    },
    {
        "Class": "Booth",
        "Id": "Fruit",
        "MaxUnitPrice": 57246
    },
    {
        "Class": "Booth",
        "Id": "Throne",
        "MaxUnitPrice": 23320036
    },
    {
        "Class": "Booth",
        "Id": "Monkey",
        "MaxUnitPrice": 202028
    },
    {
        "Class": "Booth",
        "Id": "M10",
        "MaxUnitPrice": 10034854
    },
    {
        "Class": "Booth",
        "Id": "Cupcake",
        "MaxUnitPrice": 12614402
    },
    {
        "Class": "Booth",
        "Id": "Axolotl",
        "MaxUnitPrice": 454883
    },
    {
        "Class": "Booth",
        "Id": "TNT",
        "MaxUnitPrice": 151304
    },
    {
        "Class": "Booth",
        "Id": "Christmas",
        "MaxUnitPrice": 21763
    },
    {
        "Class": "Booth",
        "Id": "Millionaire",
        "MaxUnitPrice": 75170
    },
    {
        "Class": "Booth",
        "Id": "Balloon",
        "MaxUnitPrice": 85524
    },
    {
        "Class": "Booth",
        "Id": "Lucky Block",
        "MaxUnitPrice": 170492
    },
    {
        "Class": "Booth",
        "Id": "Comet",
        "MaxUnitPrice": 7096324
    },
    {
        "Class": "Booth",
        "Id": "Haunted",
        "MaxUnitPrice": 83026
    },
    {
        "Class": "Booth",
        "Id": "Corgi",
        "MaxUnitPrice": 372764
    },
    {
        "Class": "Booth",
        "Id": "Giraffe",
        "MaxUnitPrice": 23140
    },
    {
        "Class": "Booth",
        "Id": "Egg",
        "MaxUnitPrice": 7228
    },
    {
        "Class": "Booth",
        "Id": "Abyssal",
        "MaxUnitPrice": 4153549
    },
    {
        "Class": "Booth",
        "Id": "Parrot",
        "MaxUnitPrice": 315804
    },
    {
        "Class": "Booth",
        "Id": "Present",
        "MaxUnitPrice": 53487436
    },
    {
        "Class": "Booth",
        "Id": "Hippomelon",
        "MaxUnitPrice": 20357
    },
    {
        "Class": "Booth",
        "Id": "Lightning",
        "MaxUnitPrice": 23676
    },
    {
        "Class": "Booth",
        "Id": "Rainbow",
        "MaxUnitPrice": 16527
    },
    {
        "Class": "Booth",
        "Id": "Panda",
        "MaxUnitPrice": 2216586
    },
    {
        "Class": "Booth",
        "Id": "Gold",
        "MaxUnitPrice": 16897
    },
    {
        "Class": "Booth",
        "Id": "Unicorn",
        "MaxUnitPrice": 1918242
    },
    {
        "Class": "Booth",
        "Id": "Glitched",
        "MaxUnitPrice": 3723280
    },
    {
        "Class": "Booth",
        "Id": "Pixel",
        "MaxUnitPrice": 9449805
    },
    {
        "Class": "Booth",
        "Id": "Fragmented",
        "MaxUnitPrice": 7469228
    },
    {
        "Class": "Booth",
        "Id": "Neon Twilight",
        "MaxUnitPrice": 7166123
    },
    {
        "Class": "Booth",
        "Id": "Empyrean",
        "MaxUnitPrice": 9126649
    },
    {
        "Class": "Booth",
        "Id": "Dragon",
        "MaxUnitPrice": 16902
    },
    {
        "Class": "Booth",
        "Id": "Night Terror",
        "MaxUnitPrice": 340844
    },
    {
        "Class": "Booth",
        "Id": "Fishing",
        "MaxUnitPrice": 57238
    },
    {
        "Class": "Booth",
        "Id": "Pop Cat",
        "MaxUnitPrice": 223500
    },
    {
        "Class": "Booth",
        "Id": "Alien",
        "MaxUnitPrice": 6973164
    },
    {
        "Class": "Booth",
        "Id": "Art",
        "MaxUnitPrice": 66024
    },
    {
        "Class": "Booth",
        "Id": "Bubble",
        "MaxUnitPrice": 9859723
    },
    {
        "Class": "Booth",
        "Id": "Dino Cat",
        "MaxUnitPrice": 32417
    },
    {
        "Class": "Booth",
        "Id": "Cardboard",
        "MaxUnitPrice": 6276845
    },
    {
        "Class": "Booth",
        "Id": "Rave Crab",
        "MaxUnitPrice": 17259379
    },
    {
        "Class": "Booth",
        "Id": "Hotdog",
        "MaxUnitPrice": 6203777
    },
    {
        "Class": "Booth",
        "Id": "Safety",
        "MaxUnitPrice": 23526570
    },
    {
        "Class": "Booth",
        "Id": "Black Hole",
        "MaxUnitPrice": 14516800
    },
    {
        "Class": "Booth",
        "Id": "Ice Cream",
        "MaxUnitPrice": 8060886
    },
    {
        "Class": "Booth",
        "Id": "Summer",
        "MaxUnitPrice": 33886
    },
    {
        "Class": "Booth",
        "Id": "Lemonade",
        "MaxUnitPrice": 5664042
    },
    {
        "Class": "Booth",
        "Id": "Hacker",
        "MaxUnitPrice": 288055
    },
    {
        "Class": "Booth",
        "Id": "Cat",
        "MaxUnitPrice": 130461
    },
    {
        "Class": "Booth",
        "Id": "Wicked",
        "MaxUnitPrice": 16033490
    },
    {
        "Class": "Booth",
        "Id": "Good vs Evil",
        "MaxUnitPrice": 82239
    },
    {
        "Class": "Booth",
        "Id": "Rave",
        "MaxUnitPrice": 95695
    },
    {
        "Class": "Booth",
        "Id": "Nightmare Cat",
        "MaxUnitPrice": 2020397
    },
    {
        "Class": "Booth",
        "Id": "Dino",
        "MaxUnitPrice": 26896
    },
    {
        "Class": "Booth",
        "Id": "Clown",
        "MaxUnitPrice": 30799368
    },
    {
        "Class": "Booth",
        "Id": "Aura",
        "MaxUnitPrice": 128969
    },
    {
        "Class": "Booth",
        "Id": "Enchant",
        "MaxUnitPrice": 73884
    },
    {
        "Class": "Booth",
        "Id": "Error",
        "MaxUnitPrice": 17371
    },
    {
        "Class": "Booth",
        "Id": "Merchant",
        "MaxUnitPrice": 16422
    },
    {
        "Class": "Booth",
        "Id": "Kawaii",
        "MaxUnitPrice": 21747
    },
    {
        "Class": "Enchant",
        "Id": "Superior Chest Mimic",
        "MaxUnitPrice": 115598593
    },
    {
        "Class": "Enchant",
        "Id": "Corruption",
        "MaxUnitPrice": 40827528
    },
    {
        "Class": "Enchant",
        "Id": "Nightmare Orb",
        "MaxUnitPrice": 27715245
    },
    {
        "Class": "Enchant",
        "Id": "Mini Chest Fortune",
        "MaxUnitPrice": 1318681
    },
    {
        "Class": "Enchant",
        "Id": "Shiny Supercharge",
        "MaxUnitPrice": 398933
    },
    {
        "Class": "Enchant",
        "Id": "Lightning Orb",
        "MaxUnitPrice": 33059644
    },
    {
        "Class": "Enchant",
        "Id": "Super Magnet",
        "MaxUnitPrice": 179584115
    },
    {
        "Class": "Enchant",
        "Id": "Boss Chest Mimic",
        "MaxUnitPrice": 31655178
    },
    {
        "Class": "Enchant",
        "Id": "Magic Orb",
        "MaxUnitPrice": 460239
    },
    {
        "Class": "Enchant",
        "Id": "Large Taps",
        "MaxUnitPrice": 85
    },
    {
        "Class": "Enchant",
        "Id": "Diamond Chest Mimic",
        "MaxUnitPrice": 58684598
    },
    {
        "Class": "Enchant",
        "Id": "Party Time",
        "MaxUnitPrice": 6653688
    },
    {
        "Class": "Enchant",
        "Id": "Exotic Pet",
        "MaxUnitPrice": 506
    },
    {
        "Class": "Enchant",
        "Id": "Starfall",
        "MaxUnitPrice": 256979
    },
    {
        "Class": "Enchant",
        "Id": "Super Shiny Hunter",
        "MaxUnitPrice": 157080684
    },
    {
        "Class": "Enchant",
        "Id": "Huge Hunter",
        "MaxUnitPrice": 3370063
    },
    {
        "Class": "Enchant",
        "Id": "Lightning",
        "MaxUnitPrice": 267
    },
    {
        "Class": "Enchant",
        "Id": "Fireworks",
        "MaxUnitPrice": 14380
    },
    {
        "Class": "Enchant",
        "Id": "Fortune",
        "MaxUnitPrice": 316
    },
    {
        "Class": "Enchant",
        "Id": "Explosive",
        "MaxUnitPrice": 234
    },
    {
        "Class": "Enchant",
        "Id": "Midas Touch",
        "MaxUnitPrice": 572
    },
    {
        "Class": "Enchant",
        "Id": "Fruity",
        "MaxUnitPrice": 9728
    },
    {
        "Class": "Enchant",
        "Id": "Lucky Block",
        "MaxUnitPrice": 8035539
    },
    {
        "Class": "Enchant",
        "Id": "Massive Comet",
        "MaxUnitPrice": 13139507
    },
    {
        "Class": "Enchant",
        "Id": "Chest Mimic",
        "MaxUnitPrice": 382703157
    },
    {
        "Class": "Enchant",
        "Id": "Boss Lucky Block",
        "MaxUnitPrice": 72643192
    },
    {
        "Class": "Enchant",
        "Id": "Shiny Hunter",
        "MaxUnitPrice": 199715
    },
    {
        "Class": "Enchant",
        "Id": "Super Lightning",
        "MaxUnitPrice": 1124
    },
    {
        "Class": "Lootbox",
        "Id": "Pumpkin Gift",
        "MaxUnitPrice": 15083
    },
    {
        "Class": "Lootbox",
        "Id": "Candy Corn Gift",
        "MaxUnitPrice": 5133
    },
    {
        "Class": "Lootbox",
        "Id": "Color Gift",
        "MaxUnitPrice": 19658
    },
    {
        "Class": "Lootbox",
        "Id": "Graffiti Gift",
        "MaxUnitPrice": 18656
    },
    {
        "Class": "Lootbox",
        "Id": "Meteor Gift",
        "MaxUnitPrice": 40211
    },
    {
        "Class": "Lootbox",
        "Id": "Rave Gift",
        "MaxUnitPrice": 43529
    },
    {
        "Class": "Lootbox",
        "Id": "Good vs Evil Gift",
        "MaxUnitPrice": 39571
    },
    {
        "Class": "Lootbox",
        "Id": "Good Gift",
        "MaxUnitPrice": 40468
    },
    {
        "Class": "Lootbox",
        "Id": "Evil Gift",
        "MaxUnitPrice": 36258
    },
    {
        "Class": "Lootbox",
        "Id": "Elemental Gift",
        "MaxUnitPrice": 27687
    },
    {
        "Class": "Lootbox",
        "Id": "Glitched Gift",
        "MaxUnitPrice": 454840
    },
    {
        "Class": "Lootbox",
        "Id": "Global Event Gift",
        "MaxUnitPrice": 561511
    },
    {
        "Class": "Lootbox",
        "Id": "X-Large Christmas Present",
        "MaxUnitPrice": 309572
    },
    {
        "Class": "Lootbox",
        "Id": "Medium Christmas Present",
        "MaxUnitPrice": 26225
    },
    {
        "Class": "Lootbox",
        "Id": "Summer Gift",
        "MaxUnitPrice": 168566
    },
    {
        "Class": "Lootbox",
        "Id": "Small Christmas Present",
        "MaxUnitPrice": 30245
    },
    {
        "Class": "Lootbox",
        "Id": "Large Christmas Present",
        "MaxUnitPrice": 92199
    },
    {
        "Class": "Lootbox",
        "Id": "Arcade Egg 1",
        "MaxUnitPrice": 997
    },
    {
        "Class": "Lootbox",
        "Id": "Arcade Egg 2",
        "MaxUnitPrice": 7108
    },
    {
        "Class": "Lootbox",
        "Id": "Titanic Christmas Present",
        "MaxUnitPrice": 20534383
    },
    {
        "Class": "Lootbox",
        "Id": "Adventurer Lootbox",
        "MaxUnitPrice": 3093931
    },
    {
        "Class": "Lootbox",
        "Id": "Clan Gift",
        "MaxUnitPrice": 543964
    },
    {
        "Class": "Lootbox",
        "Id": "2024 New Years Gift",
        "MaxUnitPrice": 607904
    },
    {
        "Class": "Lootbox",
        "Id": "Arcade Egg 3",
        "MaxUnitPrice": 13655
    },
    {
        "Class": "Lootbox",
        "Id": "Dino Gift",
        "MaxUnitPrice": 36492
    },
    {
        "Class": "Lootbox",
        "Id": "Arcade Egg 4",
        "MaxUnitPrice": 24360
    },
    {
        "Class": "Lootbox",
        "Id": "Arcade Egg 5",
        "MaxUnitPrice": 182779
    },
    {
        "Class": "Lootbox",
        "Id": "Hype Egg",
        "MaxUnitPrice": 104039
    },
    {
        "Class": "Ultimate",
        "Id": "UFO",
        "MaxUnitPrice": 9728972
    },
    {
        "Class": "Ultimate",
        "Id": "Lightning Storm",
        "MaxUnitPrice": 187371
    },
    {
        "Class": "Ultimate",
        "Id": "Chest Spell",
        "MaxUnitPrice": 22107308
    },
    {
        "Class": "Ultimate",
        "Id": "Hidden Treasure",
        "MaxUnitPrice": 507151927
    },
    {
        "Class": "Ultimate",
        "Id": "Tornado",
        "MaxUnitPrice": 814697
    },
    {
        "Class": "Ultimate",
        "Id": "Nightmare",
        "MaxUnitPrice": 22905655
    },
    {
        "Class": "Ultimate",
        "Id": "TNT Shower",
        "MaxUnitPrice": 74278
    },
    {
        "Class": "Ultimate",
        "Id": "Tsunami",
        "MaxUnitPrice": 3016523
    },
    {
        "Class": "Ultimate",
        "Id": "Black Hole",
        "MaxUnitPrice": 201420917
    },
                {
                    "Class": "Charm",
                    "MaxUnitPrice": 500,
                    "RapBuy": true
                },
                {
                    "Class": "Fruit",
                    "MaxUnitPrice": 10,
                    "RapBuy": true
                },
                {
                    "Class": "Egg",
                    "MaxUnitPrice": 1000000,
                    "RapBuy": true
                },
                {
                    "Class": "Hoverboard",
                    "MaxUnitPrice": 1000000,
                    "RapBuy": true
                }
            ]
        }
    }
}
